<?xml version="1.0"?><diseaseprevalences><prevalence><age>0</age><sex>0</sex><percent>0.0</percent></prevalence><prevalence><age>0</age><sex>1</sex><percent>0.0</percent></prevalence><prevalence><age>1</age><sex>0</sex><percent>0.0</percent></prevalence><prevalence><age>1</age><sex>1</sex><percent>0.0</percent></prevalence><prevalence><age>2</age><sex>0</sex><percent>0.0</percent></prevalence><prevalence><age>2</age><sex>1</sex><percent>0.0</percent></prevalence><prevalence><age>3</age><sex>0</sex><percent>0.0</percent></prevalence><prevalence><age>3</age><sex>1</sex><percent>0.0</percent></prevalence><prevalence><age>4</age><sex>0</sex><percent>0.0</percent></prevalence><prevalence><age>4</age><sex>1</sex><percent>0.0</percent></prevalence><prevalence><age>5</age><sex>0</sex><percent>0.0</percent></prevalence><prevalence><age>5</age><sex>1</sex><percent>0.0</percent></prevalence><prevalence><age>6</age><sex>0</sex><percent>0.0</percent></prevalence><prevalence><age>6</age><sex>1</sex><percent>0.0</percent></prevalence><prevalence><age>7</age><sex>0</sex><percent>0.0</percent></prevalence><prevalence><age>7</age><sex>1</sex><percent>0.0</percent></prevalence><prevalence><age>8</age><sex>0</sex><percent>0.0</percent></prevalence><prevalence><age>8</age><sex>1</sex><percent>0.0</percent></prevalence><prevalence><age>9</age><sex>0</sex><percent>0.0</percent></prevalence><prevalence><age>9</age><sex>1</sex><percent>0.0</percent></prevalence><prevalence><age>10</age><sex>0</sex><percent>0.0</percent></prevalence><prevalence><age>10</age><sex>1</sex><percent>0.0</percent></prevalence><prevalence><age>11</age><sex>0</sex><percent>0.0</percent></prevalence><prevalence><age>11</age><sex>1</sex><percent>0.0</percent></prevalence><prevalence><age>12</age><sex>0</sex><percent>0.0</percent></prevalence><prevalence><age>12</age><sex>1</sex><percent>0.0</percent></prevalence><prevalence><age>13</age><sex>0</sex><percent>0.0</percent></prevalence><prevalence><age>13</age><sex>1</sex><percent>0.0</percent></prevalence><prevalence><age>14</age><sex>0</sex><percent>0.0</percent></prevalence><prevalence><age>14</age><sex>1</sex><percent>0.0</percent></prevalence><prevalence><age>15</age><sex>0</sex><percent>0.0</percent></prevalence><prevalence><age>15</age><sex>1</sex><percent>0.0</percent></prevalence><prevalence><age>16</age><sex>0</sex><percent>0.0</percent></prevalence><prevalence><age>16</age><sex>1</sex><percent>0.0</percent></prevalence><prevalence><age>17</age><sex>0</sex><percent>0.0</percent></prevalence><prevalence><age>17</age><sex>1</sex><percent>0.0</percent></prevalence><prevalence><age>18</age><sex>0</sex><percent>0.0</percent></prevalence><prevalence><age>18</age><sex>1</sex><percent>0.0</percent></prevalence><prevalence><age>19</age><sex>0</sex><percent>0.0</percent></prevalence><prevalence><age>19</age><sex>1</sex><percent>0.0</percent></prevalence><prevalence><age>20</age><sex>0</sex><percent>0.0</percent></prevalence><prevalence><age>20</age><sex>1</sex><percent>0.0</percent></prevalence><prevalence><age>21</age><sex>0</sex><percent>0.0</percent></prevalence><prevalence><age>21</age><sex>1</sex><percent>0.0</percent></prevalence><prevalence><age>22</age><sex>0</sex><percent>0.0</percent></prevalence><prevalence><age>22</age><sex>1</sex><percent>0.0</percent></prevalence><prevalence><age>23</age><sex>0</sex><percent>0.0</percent></prevalence><prevalence><age>23</age><sex>1</sex><percent>0.0</percent></prevalence><prevalence><age>24</age><sex>0</sex><percent>0.0</percent></prevalence><prevalence><age>24</age><sex>1</sex><percent>0.0</percent></prevalence><prevalence><age>25</age><sex>0</sex><percent>0.0</percent></prevalence><prevalence><age>25</age><sex>1</sex><percent>0.0</percent></prevalence><prevalence><age>26</age><sex>0</sex><percent>0.0</percent></prevalence><prevalence><age>26</age><sex>1</sex><percent>0.0</percent></prevalence><prevalence><age>27</age><sex>0</sex><percent>0.0</percent></prevalence><prevalence><age>27</age><sex>1</sex><percent>0.0</percent></prevalence><prevalence><age>28</age><sex>0</sex><percent>0.0</percent></prevalence><prevalence><age>28</age><sex>1</sex><percent>0.0</percent></prevalence><prevalence><age>29</age><sex>0</sex><percent>0.0</percent></prevalence><prevalence><age>29</age><sex>1</sex><percent>0.0</percent></prevalence><prevalence><age>30</age><sex>0</sex><percent>0.0</percent></prevalence><prevalence><age>30</age><sex>1</sex><percent>0.0</percent></prevalence><prevalence><age>31</age><sex>0</sex><percent>0.0</percent></prevalence><prevalence><age>31</age><sex>1</sex><percent>0.0</percent></prevalence><prevalence><age>32</age><sex>0</sex><percent>0.0</percent></prevalence><prevalence><age>32</age><sex>1</sex><percent>0.0</percent></prevalence><prevalence><age>33</age><sex>0</sex><percent>0.0</percent></prevalence><prevalence><age>33</age><sex>1</sex><percent>0.0</percent></prevalence><prevalence><age>34</age><sex>0</sex><percent>0.0</percent></prevalence><prevalence><age>34</age><sex>1</sex><percent>0.0</percent></prevalence><prevalence><age>35</age><sex>0</sex><percent>0.083088</percent></prevalence><prevalence><age>35</age><sex>1</sex><percent>0.265189</percent></prevalence><prevalence><age>36</age><sex>0</sex><percent>0.090382</percent></prevalence><prevalence><age>36</age><sex>1</sex><percent>0.260388</percent></prevalence><prevalence><age>37</age><sex>0</sex><percent>0.098874</percent></prevalence><prevalence><age>37</age><sex>1</sex><percent>0.258049</percent></prevalence><prevalence><age>38</age><sex>0</sex><percent>0.108742</percent></prevalence><prevalence><age>38</age><sex>1</sex><percent>0.258018</percent></prevalence><prevalence><age>39</age><sex>0</sex><percent>0.120195</percent></prevalence><prevalence><age>39</age><sex>1</sex><percent>0.260204</percent></prevalence><prevalence><age>40</age><sex>0</sex><percent>0.13348</percent></prevalence><prevalence><age>40</age><sex>1</sex><percent>0.264571</percent></prevalence><prevalence><age>41</age><sex>0</sex><percent>0.148882</percent></prevalence><prevalence><age>41</age><sex>1</sex><percent>0.271134</percent></prevalence><prevalence><age>42</age><sex>0</sex><percent>0.166735</percent></prevalence><prevalence><age>42</age><sex>1</sex><percent>0.279954</percent></prevalence><prevalence><age>43</age><sex>0</sex><percent>0.187427</percent></prevalence><prevalence><age>43</age><sex>1</sex><percent>0.29114</percent></prevalence><prevalence><age>44</age><sex>0</sex><percent>0.211406</percent></prevalence><prevalence><age>44</age><sex>1</sex><percent>0.304842</percent></prevalence><prevalence><age>45</age><sex>0</sex><percent>0.239191</percent></prevalence><prevalence><age>45</age><sex>1</sex><percent>0.321258</percent></prevalence><prevalence><age>46</age><sex>0</sex><percent>0.271377</percent></prevalence><prevalence><age>46</age><sex>1</sex><percent>0.340633</percent></prevalence><prevalence><age>47</age><sex>0</sex><percent>0.30865</percent></prevalence><prevalence><age>47</age><sex>1</sex><percent>0.363264</percent></prevalence><prevalence><age>48</age><sex>0</sex><percent>0.351792</percent></prevalence><prevalence><age>48</age><sex>1</sex><percent>0.389498</percent></prevalence><prevalence><age>49</age><sex>0</sex><percent>0.401693</percent></prevalence><prevalence><age>49</age><sex>1</sex><percent>0.419743</percent></prevalence><prevalence><age>50</age><sex>0</sex><percent>0.459358</percent></prevalence><prevalence><age>50</age><sex>1</sex><percent>0.454468</percent></prevalence><prevalence><age>51</age><sex>0</sex><percent>0.525922</percent></prevalence><prevalence><age>51</age><sex>1</sex><percent>0.494208</percent></prevalence><prevalence><age>52</age><sex>0</sex><percent>0.60265</percent></prevalence><prevalence><age>52</age><sex>1</sex><percent>0.539573</percent></prevalence><prevalence><age>53</age><sex>0</sex><percent>0.690946</percent></prevalence><prevalence><age>53</age><sex>1</sex><percent>0.591247</percent></prevalence><prevalence><age>54</age><sex>0</sex><percent>0.792358</percent></prevalence><prevalence><age>54</age><sex>1</sex><percent>0.649995</percent></prevalence><prevalence><age>55</age><sex>0</sex><percent>0.908568</percent></prevalence><prevalence><age>55</age><sex>1</sex><percent>0.716667</percent></prevalence><prevalence><age>56</age><sex>0</sex><percent>1.041391</percent></prevalence><prevalence><age>56</age><sex>1</sex><percent>0.792201</percent></prevalence><prevalence><age>57</age><sex>0</sex><percent>1.192755</percent></prevalence><prevalence><age>57</age><sex>1</sex><percent>0.87762</percent></prevalence><prevalence><age>58</age><sex>0</sex><percent>1.364678</percent></prevalence><prevalence><age>58</age><sex>1</sex><percent>0.974031</percent></prevalence><prevalence><age>59</age><sex>0</sex><percent>1.559236</percent></prevalence><prevalence><age>59</age><sex>1</sex><percent>1.08262</percent></prevalence><prevalence><age>60</age><sex>0</sex><percent>1.778511</percent></prevalence><prevalence><age>60</age><sex>1</sex><percent>1.20464</percent></prevalence><prevalence><age>61</age><sex>0</sex><percent>2.024535</percent></prevalence><prevalence><age>61</age><sex>1</sex><percent>1.341397</percent></prevalence><prevalence><age>62</age><sex>0</sex><percent>2.299213</percent></prevalence><prevalence><age>62</age><sex>1</sex><percent>1.494225</percent></prevalence><prevalence><age>63</age><sex>0</sex><percent>2.604238</percent></prevalence><prevalence><age>63</age><sex>1</sex><percent>1.66446</percent></prevalence><prevalence><age>64</age><sex>0</sex><percent>2.940987</percent></prevalence><prevalence><age>64</age><sex>1</sex><percent>1.853399</percent></prevalence><prevalence><age>65</age><sex>0</sex><percent>3.310413</percent></prevalence><prevalence><age>65</age><sex>1</sex><percent>2.062254</percent></prevalence><prevalence><age>66</age><sex>0</sex><percent>3.71292</percent></prevalence><prevalence><age>66</age><sex>1</sex><percent>2.2921</percent></prevalence><prevalence><age>67</age><sex>0</sex><percent>4.148242</percent></prevalence><prevalence><age>67</age><sex>1</sex><percent>2.543804</percent></prevalence><prevalence><age>68</age><sex>0</sex><percent>4.615325</percent></prevalence><prevalence><age>68</age><sex>1</sex><percent>2.817956</percent></prevalence><prevalence><age>69</age><sex>0</sex><percent>5.112216</percent></prevalence><prevalence><age>69</age><sex>1</sex><percent>3.114792</percent></prevalence><prevalence><age>70</age><sex>0</sex><percent>5.635973</percent></prevalence><prevalence><age>70</age><sex>1</sex><percent>3.434104</percent></prevalence><prevalence><age>71</age><sex>0</sex><percent>6.182597</percent></prevalence><prevalence><age>71</age><sex>1</sex><percent>3.775163</percent></prevalence><prevalence><age>72</age><sex>0</sex><percent>6.747005</percent></prevalence><prevalence><age>72</age><sex>1</sex><percent>4.136636</percent></prevalence><prevalence><age>73</age><sex>0</sex><percent>7.323035</percent></prevalence><prevalence><age>73</age><sex>1</sex><percent>4.516515</percent></prevalence><prevalence><age>74</age><sex>0</sex><percent>7.903505</percent></prevalence><prevalence><age>74</age><sex>1</sex><percent>4.912063</percent></prevalence><prevalence><age>75</age><sex>0</sex><percent>8.480305</percent></prevalence><prevalence><age>75</age><sex>1</sex><percent>5.319775</percent></prevalence><prevalence><age>76</age><sex>0</sex><percent>9.044549</percent></prevalence><prevalence><age>76</age><sex>1</sex><percent>5.735372</percent></prevalence><prevalence><age>77</age><sex>0</sex><percent>9.586752</percent></prevalence><prevalence><age>77</age><sex>1</sex><percent>6.153814</percent></prevalence><prevalence><age>78</age><sex>0</sex><percent>10.09705</percent></prevalence><prevalence><age>78</age><sex>1</sex><percent>6.569357</percent></prevalence><prevalence><age>79</age><sex>0</sex><percent>10.56546</percent></prevalence><prevalence><age>79</age><sex>1</sex><percent>6.975639</percent></prevalence><prevalence><age>80</age><sex>0</sex><percent>10.98211</percent></prevalence><prevalence><age>80</age><sex>1</sex><percent>7.365796</percent></prevalence><prevalence><age>81</age><sex>0</sex><percent>11.33752</percent></prevalence><prevalence><age>81</age><sex>1</sex><percent>7.732618</percent></prevalence><prevalence><age>82</age><sex>0</sex><percent>11.62289</percent></prevalence><prevalence><age>82</age><sex>1</sex><percent>8.068721</percent></prevalence><prevalence><age>83</age><sex>0</sex><percent>11.83032</percent></prevalence><prevalence><age>83</age><sex>1</sex><percent>8.366743</percent></prevalence><prevalence><age>84</age><sex>0</sex><percent>11.95309</percent></prevalence><prevalence><age>84</age><sex>1</sex><percent>8.619557</percent></prevalence><prevalence><age>85</age><sex>0</sex><percent>11.98585</percent></prevalence><prevalence><age>85</age><sex>1</sex><percent>8.820483</percent></prevalence><prevalence><age>86</age><sex>0</sex><percent>11.92485</percent></prevalence><prevalence><age>86</age><sex>1</sex><percent>8.963501</percent></prevalence><prevalence><age>87</age><sex>0</sex><percent>11.76816</percent></prevalence><prevalence><age>87</age><sex>1</sex><percent>9.043462</percent></prevalence><prevalence><age>88</age><sex>0</sex><percent>11.51576</percent></prevalence><prevalence><age>88</age><sex>1</sex><percent>9.056281</percent></prevalence><prevalence><age>89</age><sex>0</sex><percent>11.16972</percent></prevalence><prevalence><age>89</age><sex>1</sex><percent>8.999117</percent></prevalence><prevalence><age>90</age><sex>0</sex><percent>10.73431</percent></prevalence><prevalence><age>90</age><sex>1</sex><percent>8.870533</percent></prevalence><prevalence><age>91</age><sex>0</sex><percent>10.216</percent></prevalence><prevalence><age>91</age><sex>1</sex><percent>8.670635</percent></prevalence><prevalence><age>92</age><sex>0</sex><percent>9.623468</percent></prevalence><prevalence><age>92</age><sex>1</sex><percent>8.401174</percent></prevalence><prevalence><age>93</age><sex>0</sex><percent>8.967469</percent></prevalence><prevalence><age>93</age><sex>1</sex><percent>8.065615</percent></prevalence><prevalence><age>94</age><sex>0</sex><percent>8.260644</percent></prevalence><prevalence><age>94</age><sex>1</sex><percent>7.669159</percent></prevalence><prevalence><age>95</age><sex>0</sex><percent>7.517187</percent></prevalence><prevalence><age>95</age><sex>1</sex><percent>7.218701</percent></prevalence></diseaseprevalences>