<?xml version="1.0"?><simulation><hasnewborns>true</hasnewborns><startingYear>2009</startingYear><numberOfYears>10</numberOfYears><simPopSize>1</simPopSize><minAge>0</minAge><maxAge>95</maxAge><timeStep>1</timeStep><randomSeed>1</randomSeed><resultType>Emptyness2BFilled</resultType><popFileName>Netherlands2005</popFileName><scenarios><scenario><uniquename>Scenario1</uniquename><successRate>100</successRate><targetMinAge>0</targetMinAge><targetMaxAge>0</targetMaxAge><targetSex>0</targetSex><transfilename>NL_2005_Transition_Zero_BMI_cat3</transfilename><prevfilename>NL_2005_RF_BMI_cat3_minimumwage</prevfilename></scenario></scenarios><diseases><disease><uniquename>NL_2005_IHD</uniquename><prevfilename>NL2005_Disease_IHD_Inc_4_09_2009</prevfilename><incfilename>NL2005_Disease_IHD_Inc_4_09_2009</incfilename><excessmortfilename>NL2005_Disease_IHD_Inc_4_09_2009</excessmortfilename><dalyweightsfilename>NL2005_Disease_IHD_DALY_4_09_2009</dalyweightsfilename></disease><disease><uniquename>cancer_breast</uniquename><prevfilename>Disease prevalence_ca breast</prevfilename><incfilename>Disease incidence_ca breast</incfilename><excessmortfilename>Excess mortality_ca breast</excessmortfilename><dalyweightsfilename>DALY weights_ca breast</dalyweightsfilename></disease><disease><uniquename>cancer_oral</uniquename><prevfilename>Disease prevalence_ca oral</prevfilename><incfilename>Disease incidence_ca oral</incfilename><excessmortfilename>Excess mortality_ca oral</excessmortfilename><dalyweightsfilename>DALY weights_ca oral</dalyweightsfilename></disease><disease><uniquename>NL_2005_Diabetes</uniquename><prevfilename>NL2005_Disease_Diabetes_Inc_4_09_2009</prevfilename><incfilename>NL2005_Disease_Diabetes_Inc_4_09_2009</incfilename><excessmortfilename>NL2005_Disease_Diabetes_ExecMort_4_09_2009</excessmortfilename><dalyweightsfilename>NL2005_Disease_Diabetes_DALY_4_09_2009</dalyweightsfilename></disease><disease><uniquename>NL_2005_CancerCol</uniquename><prevfilename>NL2005_Disease_CancerOral_Prev_4_09_2009</prevfilename><incfilename>NL2005_Disease_CancerOral_Inc_4_09_2009</incfilename><excessmortfilename>NL2005_Disease_CancerOral_ExecMort_4_09_2009</excessmortfilename><dalyweightsfilename>NL2005_Disease_CancerOral_DALY_4_09_2009</dalyweightsfilename></disease></diseases><riskfactors><riskfactor><uniquename>NL_BMI_cat3</uniquename><transfilename>NL_2005_Transition_Zero_BMI_cat3</transfilename><prevfilename>NL_2005_RF_BMI_cat3</prevfilename></riskfactor></riskfactors><RRs><RR><RRindex>0</RRindex><isRRfrom>NL_BMI_cat3</isRRfrom><isRRto>NL_2005_IHD</isRRto><isRRFile>RR_to_IHD_from-NL_BMI_cat3</isRRFile></RR><RR><RRindex>1</RRindex><isRRfrom>NL_BMI_cat3</isRRfrom><isRRto>death</isRRto><isRRFile>RR_BMI_cat3_to_Death</isRRFile></RR><RR><RRindex>2</RRindex><isRRfrom>NL_BMI_cat3</isRRfrom><isRRto>NL_2005_CancerCol</isRRto><isRRFile>RR_to_CancerColRec_from-NL_BMI_cat3</isRRFile></RR><RR><RRindex>3</RRindex><isRRfrom>NL_BMI_cat3</isRRfrom><isRRto>NL_2005_Diabetes</isRRto><isRRFile>RR_to_BMI-NL_BMI_cat3</isRRFile></RR></RRs></simulation>